ds20kdb/__init__.py
ds20kdb/auth.py
ds20kdb/common.py
ds20kdb/constants.py
ds20kdb/create_credentials_file.py
ds20kdb/gen_tray_files_gui.py
ds20kdb/interface.py
ds20kdb/interface_cache.py
ds20kdb/qrgen.py
ds20kdb/scanner_auto.py
ds20kdb/submit_vtile.py
ds20kdb/submit_vtile_json.py
ds20kdb/test_common.py
ds20kdb/test_interface_database.py
ds20kdb/test_interface_utilities.py
ds20kdb/test_tray.py
ds20kdb/tray.py
ds20kdb/veto_location.py
ds20kdb/veto_location_gui.py
ds20kdb/visual.py
ds20kdb/vtile_test_submit_cr.py
ds20kdb/wafer_heat_map_from_vtile_qrcodes.py
ds20kdb/wafer_location_gui.py
ds20kdb/wafer_map_from_db.py
ds20kdb_avt-1.2.3.dist-info/licenses/LICENSE
ds20kdb_avt-1.2.3.dist-info/METADATA
ds20kdb_avt-1.2.3.dist-info/PKG-INFO.orig
ds20kdb_avt-1.2.3.dist-info/WHEEL
ds20kdb_avt-1.2.3.dist-info/entry_points.txt
ds20kdb_avt-1.2.3.dist-info/top_level.txt
ds20kdb_avt-1.2.3.dist-info/RECORD
