Metadata-Version: 2.4
Name: ds20kdb-avt
Version: 1.2.3
Summary: A cross-platform Python interface to the DarkSide-20k production database
Home-page: https://gitlab.in2p3.fr/darkside/productiondb_software/
Author: Alan Taylor, Paolo Franchini
Author-email: avt@hep.ph.liv.ac.uk
Maintainer: Alan Taylor
Maintainer-email: avt@hep.ph.liv.ac.uk
Classifier: Development Status :: 4 - Beta
Classifier: Intended Audience :: Developers
Classifier: Intended Audience :: Science/Research
Classifier: Topic :: Scientific/Engineering :: Physics
Classifier: Environment :: Console
Classifier: Environment :: X11 Applications
Classifier: Programming Language :: Python :: 3
Classifier: Programming Language :: Python :: 3 :: Only
Classifier: Programming Language :: Python :: 3.6
Classifier: Programming Language :: Python :: 3.7
Classifier: Programming Language :: Python :: 3.8
Classifier: Programming Language :: Python :: 3.9
Classifier: Programming Language :: Python :: 3.10
Classifier: Programming Language :: Python :: 3.11
Classifier: Programming Language :: Python :: 3.12
Classifier: Programming Language :: Python :: 3.13
Classifier: Operating System :: OS Independent
Classifier: Natural Language :: English
Classifier: License :: OSI Approved :: European Union Public Licence 1.2 (EUPL 1.2)
Requires-Python: >=3.6
License-File: LICENSE
Requires-Dist: aiohttp
Requires-Dist: importlib-metadata
Requires-Dist: matplotlib
Requires-Dist: pandas
Requires-Dist: pyarrow
Requires-Dist: python-dateutil>=2.9.0
Requires-Dist: requests
Requires-Dist: tkcalendar
Requires-Dist: ttkwidgets
Requires-Dist: paramiko
Requires-Dist: polars-lts-cpu
Dynamic: author
Dynamic: author-email
Dynamic: classifier
Dynamic: description
Dynamic: description-content-type
Dynamic: home-page
Dynamic: license-file
Dynamic: maintainer
Dynamic: maintainer-email
Dynamic: requires-dist
Dynamic: requires-python
Dynamic: summary
